nlp_lib/__init__.py
nlp_lib/preprocessor.py
nlpProcessor-0.0.5.dist-info/LICENSE
nlpProcessor-0.0.5.dist-info/METADATA
nlpProcessor-0.0.5.dist-info/WHEEL
nlpProcessor-0.0.5.dist-info/top_level.txt
nlpProcessor-0.0.5.dist-info/RECORD
