Metadata-Version: 2.1
Name: nlpProcessor
Version: 0.0.5
Summary: Natural language processing package
Author: Afnanurrahim Ansari
Author-email: afnanurrahim150102@gmail.com
Keywords: nlp,natural language processing,processor
Classifier: Development Status :: 1 - Planning
Classifier: Intended Audience :: Developers
Classifier: Programming Language :: Python :: 3
Classifier: Operating System :: Unix
Classifier: Operating System :: MacOS :: MacOS X
Classifier: Operating System :: Microsoft :: Windows
License-File: LICENSE
Requires-Dist: pandas
Requires-Dist: emoji
